Workbook

Sheet Affordability Calculator
A1: TEREPAY AFFORDABILITY CALCULATOR
A2: CCCFA Compliance Tool - v1.0
A4: SECTION A: CUSTOMER INFORMATION
A5: Customer Name:
A6: Loan Amount Requested:
A7: Loan Purpose:
A8: Assessment Date: | B8: =TODAY() -> 46055
A9: Assessed By:
A11: Employment & Visa Details
A12: Employment Status: | B12: Permanent/Fixed-term/Casual
A13: Employer:
A14: Time with Employer (months):
A16: Visa Status: | B16: NZ Citizen/Resident or Temporary
A17: Visa Type (if temporary):
A18: Visa Expiry Date:
A19: Valid 3+ months beyond loan? | B19: YES/NO
A21: Centrix Report Details
A22: Report Number:
A23: Report Date:
A24: First Transaction Date:
A25: Days of Data: | B25: =B23-B24 -> 0
A26: 90+ Days? | B26: =IF(B25>=90,"✓ PASS","✗ FAIL - DECLINE") -> ✗ FAIL - DECLINE
A27: ⚠️ CRITICAL: If less than 90 days, DECLINE application
A29: SECTION B: INCOME VERIFICATION
A30: Income Source | B30: Centrix Amount ($/fn) | C30: Verified (Y/N) | D30: Adjusted Amount ($/fn)
A31: Salary/Wages | D31: =IF(B31="","",B31)
A32: Bonuses | D32: =IF(B32="","",B32)
A33: Rental Income | D33: =IF(B33="","",B33)
A34: Benefits/WINZ | D34: =IF(B34="","",B34)
A35: Partner Income | D35: =IF(B35="","",B35)
A36: Other Income | D36: =IF(B36="","",B36)
A37: TOTAL VERIFIED INCOME | D37: =SUM(D31:D36) -> 0
A39: SECTION C: EXPENSE VERIFICATION & ADJUSTMENTS
A40: Expense Category | B40: Centrix ($/fn) | C40: Benchmark ($/fn) | D40: Final Amount ($/fn)
A41: ESSENTIAL LIVING
A42: Food & Groceries | C42: =Benchmarks!B4 -> Per Fortnight | D42: =IF(B42="",C42,MAX(B42,C42)) -> Per Fortnight
A43: Utilities (power, water, internet) | C43: =Benchmarks!B5 -> 280 | D43: =IF(B43="",C43,MAX(B43,C43)) -> 280
A44: Personal expenses (clothing, footwear) | C44: =Benchmarks!B6 -> 100 | D44: =IF(B44="",C44,MAX(B44,C44)) -> 100
A45: Transport (fuel, WoF/rego, maintenance) | C45: =Benchmarks!B7 -> 80 | D45: =IF(B45="",C45,MAX(B45,C45)) -> 80
A46: Medical (GP, prescriptions) | C46: =Benchmarks!B8 -> 200 | D46: =IF(B46="",C46,MAX(B46,C46)) -> 200
A47: Childcare / dependants | C47: =Benchmarks!B9 -> 60 | D47: =IF(B47="",C47,MAX(B47,C47)) -> 60
A49: FIXED FINANCIAL
A50: Accommodation (Rent/Mortgage Payments) | C50: N/A | D50: =IF(B50="",0,B50) -> 0
A51: Home and Insurance | C51: N/A | D51: =IF(B51="",0,B51) -> 0
A52: Rates/Body Corporate | C52: N/A | D52: =IF(B52="",0,B52) -> 0
A53: Education Costs | C53: N/A | D53: =IF(B53="",0,B53) -> 0
A55: DEBT PAYMENTS
A56: Mortgage Payment | C56: N/A | D56: =IF(B56="",0,B56) -> 0
A57: VehiclePayment | C57: N/A | D57: =IF(B57="",0,B57) -> 0
A58: Personal Payment | C58: N/A | D58: =IF(B58="",0,B58) -> 0
A59: Credit Cards (min payment) | C59: N/A | D59: =IF(B59="",0,B59) -> 0
A60: BNPL repayments & other debts
A61: Other Debts | C61: N/A | D61: =IF(B61="",0,B61) -> 0
A63: ADDITIONAL EXPENSES (often missed)
A64: Overseas Remittances | C64: Manual Entry | D64: =IF(B64="",0,B64) -> 0
A65: Tithing/Church Donations | C65: Manual Entry | D65: =IF(B65="",0,B65) -> 0
A66: Car WOF (annual ÷ 26) | C66: Manual Entry | D66: =IF(B66="",0,B66) -> 0
A67: Car Registration (annual ÷ 26) | C67: Manual Entry | D67: =IF(B67="",0,B67) -> 0
A68: Other Regular Expenses | C68: Manual Entry | D68: =IF(B68="",0,B68) -> 0
A70: DISCRETIONARY
A71: Dining Out | C71: N/A | D71: =IF(B71="",0,B71) -> 0
A72: Entertainment | C72: N/A | D72: =IF(B72="",0,B72) -> 0
A73: Subscriptions | C73: N/A | D73: =IF(B73="",0,B73) -> 0
A74: Other Discretionary | C74: N/A | D74: =IF(B74="",0,B74) -> 0
A76: TOTAL ADJUSTED EXPENSES | D76: =SUM(D42:D74) -> 720
A78: SECTION D: AFFORDABILITY CALCULATION
A79: Step 1: Current Surplus
A80: Total Verified Income | D80: =D37 -> 0
A81: Minus: Total Adjusted Expenses | D81: =D76 -> 720
A82: CURRENT SURPLUS | D82: =D37-D76 -> -720
A84: Step 2: Loan Payment Calculation
A85: Loan Amount Requested
A86: Total Repayment (Loan × 1.047) | D86: =B85*1.047 -> 0
A87: FORTNIGHTLY LOAN PAYMENT (÷ 4) | D87: =(B85*1.047)/4 -> 0
A89: Step 3: Surplus After Loan Payment
A90: Current Surplus | D90: =D82 -> -720
A91: Minus: Fortnightly Loan Payment | D91: =D87 -> 0
A92: SURPLUS AFTER LOAN PAYMENT | D92: =D82-D87 -> -720
A94: Step 4: Apply 20% Safety Buffer (MANDATORY - Reg 4AF)
A95: Surplus After Loan Payment | D95: =D92 -> -720
A96: Safety Buffer Required (20%) | D96: =D92*0.2 -> -144
A98: Step 5: FINAL AVAILABLE SURPLUS
A99: Surplus After Loan Payment | D99: =D92 -> -720
A100: Minus: Safety Buffer (20%) | D100: =D96 -> -144
A101: ═══ FINAL AVAILABLE SURPLUS ═══ | D101: =D92-D96 -> -576
A103: SECTION E: DECISION & RISK ASSESSMENT
A104: Affordability Result: | B104: =IF(D101<0,"✗ NOT AFFORDABLE - DECLINE",IF(D101<50,"⚠ HIGH RISK",IF(D101<100,"⚠ MARGINAL - Careful Review","✓ LIKELY AFFORDABLE"))) -> ✗ NOT AFFORDABLE - DECLINE
A106: MANDATORY DECLINE CHECKS (Any = DECLINE):
A107: Less than 90 days data? | B107: Y/N
A108: Visa expiring before loan ends? | B108: Y/N
A109: Cannot verify income? | B109: Y/N
A110: Recent defaults (90 days)? | B110: Y/N
A111: Loan for remittances/planned expenses? | B111: Y/N
A112: Multiple existing short-term loans? | B112: Y/N
A114: FINAL DECISION: | B114: APPROVE / DECLINE / ALTERNATIVE
A115: Alternative Amount (if applicable):
A117: Decision Rationale:
A122: Assessed By:
A123: Date: | B123: =TODAY() -> 46055

Sheet Benchmarks
A1: TEREPAY EXPENSE BENCHMARKS
A2: Auckland 2026 - Single Adult (Adjust for household size)
A4: Category | B4: Per Fortnight | C4: Notes
A5: Food & Groceries | B5: 280 | C5: Range: $240-320
A6: Utilities | B6: 100 | C6: Range: $80-120 (power, water, internet)
A7: Personal/Clothing | B7: 80 | C7: Range: $60-100
A8: Transport (Car) | B8: 200 | C8: Range: $160-240 (fuel, WOF, rego, maintenance)
A9: Medical | B9: 60 | C9: Range: $40-80 (GP visits, prescriptions)
A10: Childcare | B10: 0 | C10: Preschool: $400-800, School age: $100-200
A13: HOUSEHOLD SIZE MULTIPLIERS
A14: 2 adults | B14: 1.5x
A15: 2 adults + 1 child | B15: 1.8x
A16: 2 adults + 2 children | B16: 2.0x
A17: Each additional person | B17: +0.3x

Sheet Quick Guide
A1: TEREPAY AFFORDABILITY CALCULATOR
A2: Quick Reference Guide
A4: HOW TO USE THIS CALCULATOR
A5: 1. Complete customer information (Section A)
A6: 2. Enter income from Centrix and verify (Section B)
A7: 3. Enter expenses from Centrix (Section C)
A8: - Benchmarks auto-populate - use higher of Centrix or benchmark
A9: - Add any additional expenses not in Centrix
A10: 4. Enter loan amount requested (Section D)
A11: - All calculations are automatic
A12: 5. Review Final Available Surplus
A13: - Positive = potentially affordable
... A17: LOAN PAYMENT QUICK REFERENCE
A18: Loan Amount | B18: Fortnightly Payment | C18: Total Repayment
A19: 200 | B19: 52.35 | C19: 209.4
A20: 500 | B20: 130.88 | C20: 523.5
A21: 800 | B21: 209.4 | C21: 837.6
A22: 1000 | B22: 261.75 | C22: 1047
A23: 1200 | B23: 314.1 | C23: 1256.4
A24: 1500 | B24: 392.63 | C24: 1570.5
A25: 2000 | B25: 523.5 | C25: 2094
A27: INSTANT DECLINE REASONS
A28: • Less than 90 days transaction data
A29: • Visa expiring before loan completion
A30: • Final Available Surplus ≤ $0
A31: • Cannot verify income
A32: • Recent payment defaults (90 days)
A33: • Loan purpose: overseas remittances
A34: • Loan purpose: planned expenses (visa, celebrations)
A36: AFFORDABILITY DECISION GUIDE
A37: Final Surplus | B37: Interpretation | C37: Action
A38: > $100/fortnight | B38: ✓ Likely Affordable | C38: Proceed - subject to other checks
A39: $50-$100/fortnight | B39: ⚠ Marginal | C39: Careful consideration needed
A40: $0-$50/fortnight | B40: ⚠ High Risk | C40: Likely substantial hardship
A41: < $0 (negative) | B41: ✗ Not Affordable | C41: MUST DECLINE
